LICENSE
README.md
pyproject.toml
setup.py
tests/test_main.py
tests/test_ydl.py
youtube_extract/__init__.py
youtube_extract/__main__.py
youtube_extract/ydl_utils.py
youtube_extract.egg-info/PKG-INFO
youtube_extract.egg-info/SOURCES.txt
youtube_extract.egg-info/dependency_links.txt
youtube_extract.egg-info/entry_points.txt
youtube_extract.egg-info/requires.txt
youtube_extract.egg-info/top_level.txt