Metadata-Version: 2.1
Name: youtube-extract
Version: 1.4.0
Summary: Extract metadata for all videos from a youtube channel into a csv or xlsx file.
Home-page: https://github.com/dbeley/youtube_extract
Author: dbeley
Author-email: dbeley@protonmail.com
Classifier: Programming Language :: Python :: 3
Classifier: Operating System :: POSIX :: Linux
License-File: LICENSE
Requires-Dist: yt-dlp
Requires-Dist: pandas
Requires-Dist: openpyxl
